jira/__init__.py
jira/client.py
jira/config.py
jira/exceptions.py
jira/jirashell.py
jira/resilientsession.py
jira/resources.py
jira/utils/LICENSE
jira/utils/__init__.py
jira_333-3.4.0.dist-info/AUTHORS.rst
jira_333-3.4.0.dist-info/LICENSE
jira_333-3.4.0.dist-info/METADATA
jira_333-3.4.0.dist-info/WHEEL
jira_333-3.4.0.dist-info/entry_points.txt
jira_333-3.4.0.dist-info/top_level.txt
jira_333-3.4.0.dist-info/RECORD
