Metadata-Version: 2.1
Name: jira-333
Version: 3.4.0
Summary: Python library for interacting with Jira via REST APIs.
Home-page: https://github.com/pycontribs/jira
Author: Ben Speakmon
Author-email: ben.speakmon@gmail.com
Maintainer: Sorin Sbarnea
Maintainer-email: sorin.sbarnea@gmail.com
License: BSD
Project-URL: Bug Tracker, https://github.com/pycontribs/jira/issues
Project-URL: Release Management, https://github.com/pycontribs/jira/projects
Project-URL: CI: Travis, https://travis-ci.com/pycontribs/jira
Project-URL: Source Code, https://github.com/pycontribs/jira.git
Project-URL: Documentation, https://jira.readthedocs.io/en/master/
Project-URL: Forum, https://community.atlassian.com/t5/tag/jira-python/tg-p?sort=recent
Keywords: api,atlassian,jira,rest,web
Platform: any
Classifier: Development Status :: 5 - Production/Stable
Classifier: Environment :: Other Environment
Classifier: Intended Audience :: Developers
Classifier: Intended Audience :: Information Technology
Classifier: License :: OSI Approved :: BSD License
Classifier: Operating System :: OS Independent
Classifier: Programming Language :: Python
Classifier: Programming Language :: Python :: 3
Classifier: Programming Language :: Python :: 3 :: Only
Classifier: Programming Language :: Python :: 3.5
Classifier: Programming Language :: Python :: 3.6
Classifier: Programming Language :: Python :: 3.7
Classifier: Topic :: Software Development :: Libraries :: Python Modules
Classifier: Topic :: Internet :: WWW/HTTP
Requires-Python: >=3.5
Requires-Dist: defusedxml
Requires-Dist: keyring
Requires-Dist: requests-oauthlib (>=1.1.0)
Requires-Dist: requests (>=2.10.0)
Requires-Dist: requests-toolbelt
Requires-Dist: setuptools (>=20.10.1)
Provides-Extra: async
Requires-Dist: requests-futures (>=0.9.7) ; extra == 'async'
Provides-Extra: cli
Requires-Dist: ipython (>=4.0.0) ; extra == 'cli'
Provides-Extra: docs
Requires-Dist: Sphinx (>=2.2.0) ; extra == 'docs'
Requires-Dist: sphinx-rtd-theme (>=0.4.3) ; extra == 'docs'
Provides-Extra: opt
Requires-Dist: filemagic (>=1.6) ; extra == 'opt'
Requires-Dist: PyJWT ; extra == 'opt'
Requires-Dist: requests-jwt ; extra == 'opt'
Requires-Dist: requests-kerberos ; extra == 'opt'
Provides-Extra: test
Requires-Dist: docutils (>=0.12) ; extra == 'test'
Requires-Dist: flaky ; extra == 'test'
Requires-Dist: MarkupSafe (>=0.23) ; extra == 'test'
Requires-Dist: mypy ; extra == 'test'
Requires-Dist: oauthlib ; extra == 'test'
Requires-Dist: pre-commit ; extra == 'test'
Requires-Dist: py (>=1.4) ; extra == 'test'
Requires-Dist: pytest-cache ; extra == 'test'
Requires-Dist: pytest-cov ; extra == 'test'
Requires-Dist: pytest-instafail ; extra == 'test'
Requires-Dist: pytest-sugar ; extra == 'test'
Requires-Dist: pytest-timeout (>=1.3.1) ; extra == 'test'
Requires-Dist: pytest-xdist (>=1.14) ; extra == 'test'
Requires-Dist: pytest (<6.0,>=5.0.0) ; extra == 'test'
Requires-Dist: PyYAML (>=5.1) ; extra == 'test'
Requires-Dist: requests-mock ; extra == 'test'
Requires-Dist: requires.io ; extra == 'test'
Requires-Dist: tenacity ; extra == 'test'
Requires-Dist: wheel (>=0.24.0) ; extra == 'test'
Requires-Dist: xmlrunner (>=1.7.7) ; extra == 'test'
Requires-Dist: yanc (>=0.3.3) ; extra == 'test'
